{
    "title": "Flowmaster Force II Cat-back Exhaust System for the 1998-2003 Ford F-150 (PN 17472 and 817472)",
    "description": "Designed for the person who wants the look of a traditional dual exhaust system with all the benefits that a Flowmaster Cat-back exhaust system provides, this D.O.R.\/D.O.S. system is the perfect choice. This system includes exit pipes for both dual out rear and dual out side configurations so that you can choose the one that fits your style. This Force II system delivers a moderate exterior tone and mild interior tone, and is suited to customers looking for efficiency improvements without a lot of noise. Especially recommended for towing applications. Constructed in durable 409S stainless steel, the system is covered by a 10-year warranty. Like all Flowmaster systems, the benefits include improved throttle response, power and mileage. Designed for an easy fit, the system includes all the necessary parts and hardware for an easy installation.",
    "referenceId": "dCjAz6rgPs8",
    "date_created": "1286562676",
    "date_modified": "1453335723",
    "tags": "Ford, F150 , Exhaust",
    "sourceId": "4",
    "VIDEO_LENGTH": "SHORT",
    "year": null,
    "make": "6",
    "model": "model-174",
    "brand_video": "50380",
    "category_video": null,
    "status": "approved",
    "department": "Exhaust, Mufflers & Tips",
    "featured_video": null,
    "visibility": "1",
    "VV_VI": "31",
    "CVV_VI": null,
    "engagement_score": null,
    "conversion_score": null,
    "id": "10253631",
    "loginId": "1758237",
    "entityType": "1",
    "titleTextEncoded": "Flowmaster-Force-II-Cat-back-Exhaust-System-for-the-1998-2003-Ford-F-150-PN-17472-and-817472",
    "category": "",
    "duration": "69",
    "settings": "",
    "asset": {
        "type": "youtube",
        "thumbnailUrl": "https:\/\/i.ytimg.com\/vi\/dCjAz6rgPs8\/hqdefault.jpg",
        "uploadDate": 1286562676,
        "videoId": "dCjAz6rgPs8",
        "title": "Flowmaster Force II Cat-back Exhaust System for the 1998-2003 Ford F-150 (PN 17472 and 817472)",
        "description": "Questions? Give us a call (707) 544-4761\nTo view these products click below:\nhttp:\/\/www.flowmastermufflers.com\/?page_id=443&keywords=17472&x=0&y=0\n\nSubscribe to our Youtube channel:\nhttp:\/\/www.youtube.com\/user\/Flowmaster\n\nFor updates and new product releases, \u2018LIKE\u2019 us on Facebook: \nhttp:\/\/www.facebook.com\/FlowmasterMufflersINC\n\nFollow Flowmaster on Twitter:\nhttp:\/\/twitter.com\/flowmaster1\n\nFollow Flowmaster on Instagram:\nhttp:\/\/instagram.com\/flowmaster_official\/\n\nFeatures:\nDesigned for the person who wants the look of a traditional dual exhaust system with all the benefits that a Flowmaster Cat-back exhaust system provides, this D.O.R.\/D.O.S. system is the perfect choice. This system includes exit pipes for both dual out rear and dual out side configurations so that you can choose the one that fits your style. This Force II system delivers a moderate exterior tone and mild interior tone, and is suited to customers looking for efficiency improvements without a lot of noise. Especially recommended for towing applications. Constructed in durable 409S stainless steel, the system is covered by a 10-year warranty. Like all Flowmaster systems, the benefits include improved throttle response, power and mileage. Designed for an easy fit, the system includes all the necessary parts and hardware for an easy installation.",
        "author": "Flowmaster Inc",
        "mediaDuration": "69",
        "prettyDuration": "00:01:09",
        "views": "14165"
    },
    "transcripts": "",
    "metrics_statistics": "{\"VV_VI\":{\"lastUpdatedDate\":\"2017-05-24\",\"engagement_score\":{\"lastUpdatedDate\":\"2017-05-25\"}}}",
    "tvp_profiles": null,
    "tvp_profiles_manual": null,
    "tvp_profiles_maxscore": null
}