{
    "title": "Flowmaster's Outlaw Series Cat-back System - 2009-2016 RAM 1500",
    "description": "Flowmaster Part #817690",
    "referenceId": "d49d2_zHQrg",
    "date_created": "1399053078",
    "date_modified": "1453844527",
    "tags": "Dodge, Dodge Ram, Exhaust, Flowmaster",
    "sourceId": "4",
    "VIDEO_LENGTH": "SHORT",
    "year": null,
    "make": "23",
    "model": "model-224",
    "brand_video": "50380",
    "category_video": null,
    "status": "approved",
    "department": "Exhaust, Mufflers & Tips",
    "featured_video": null,
    "visibility": "1",
    "VV_VI": "54",
    "CVV_VI": "3",
    "engagement_score": null,
    "conversion_score": null,
    "id": "10253486",
    "loginId": "1758237",
    "entityType": "1",
    "titleTextEncoded": "Flowmaster-s-Outlaw-Series-Cat-back-System-2009-2016-RAM-1500",
    "category": "",
    "duration": "86",
    "settings": "",
    "asset": {
        "type": "youtube",
        "thumbnailUrl": "https:\/\/i.ytimg.com\/vi\/d49d2_zHQrg\/hqdefault.jpg",
        "uploadDate": 1399053078,
        "videoId": "d49d2_zHQrg",
        "title": "Flowmaster's Outlaw Series Cat-back System - 2009-2016 RAM 1500 PN 817690",
        "description": "Questions? Give us a call (707) 544-4761\nView this product: http:\/\/bit.ly\/1KyPLHK\nVisit Flowmaster's website: http:\/\/bit.ly\/1fyGZRh\n\nFlowmaster Part #817690\n\nApplication:\nFits 2009-2016 Dodge\/Ram 1500 Trucks with 4.7L or 5.7L V8 Gas Engine. Only Fits Std Cab 8' Bed, Crew Cab 5'7 Bed\n\nFeatures:\nFlowmaster's Outlaw Cat-back exhaust system for the 2009-2016 Dodge Ram 1500 truck is perfect for the person looking for maximum sound levels both inside and outside of the truck, with all of the performance benefits that you would expect from Flowmaster. This bolt-on DOR\/DOS (Dual Out Rear or Dual Out Side) emissions-legal system for trucks with the 4.7L and 5.7L V8 engine features a stainless steel Super 10 Series muffler and dual mandrel bent 3.00\" stainless steel tailpipes for maximum sound and performance. The system also features Black Ceramic coated 4.00\" double wall stainless steel tips. The exhaust system is manufactured in the USA and is covered by Flowmaster's Lifetime Limited Warranty. Designed for an easy fit, this system includes all necessary parts and hardware for installation. Note: Fits Std Cab\/8' Bed, Crew Cab\/5'7\" Bed, and Quad Cab\/6'4? Bed trucks.\n\u2713 Stainless Steel Construction\n\u2713 Super Aggressive Sound\n\u2713 Black Ceramic Coated Tips\n\u2713 Lifetime Limited Warranty\n\u2713 Made in the USA\n\nFollow Flowmaster on Instagram:\nhttp:\/\/bit.ly\/1LsFNvT\n\nFor updates and new product releases, \u2018LIKE\u2019 us on Facebook: \nhttp:\/\/on.fb.me\/1K955xg\n\nFollow Flowmaster on Twitter:\nhttp:\/\/bit.ly\/1FBjnAu\n\nSubscribe to our Youtube channel:\nhttp:\/\/bit.ly\/1RuFMGB",
        "author": "Flowmaster Inc",
        "mediaDuration": "86",
        "prettyDuration": "00:01:26",
        "views": "88475"
    },
    "transcripts": "",
    "metrics_statistics": "{\"VV_VI\":{\"lastUpdatedDate\":\"2017-05-24\",\"engagement_score\":{\"lastUpdatedDate\":\"2017-05-25\"}},\"CVV_VI\":{\"lastUpdatedDate\":\"2017-05-24\",\"conversion_score\":{\"lastUpdatedDate\":\"2017-05-25\"}}}",
    "tvp_profiles": null,
    "tvp_profiles_manual": null,
    "tvp_profiles_maxscore": null
}