{
    "title": "Flowmaster Force II Cat-back Exhaust System 11-14 Ford F-150 3.5L EcoBoost - 817539",
    "description": "Questions? Give us a call (707) 544-4761\nView this product: http:\/\/bit.ly\/1fZppXj\nVisit Flowmaster's website: http:\/\/bit.ly\/1fyGZRh\n\nFlowmaster Part #817539\n\nTest Vehicle: 2014 Ford F-150 3.5L\n\nApplication:\n2011 to 2014 Ford F-150 with a 3.5L Eco Boost Turbo V6 engine, fits all wheelbases.\n\nFeatures:\nFor the person who wants the look of a traditional dual exhaust system with all the benefits that a Flowmaster Cat-back exhaust system provides, DOR\/S systems are the perfect choice. This system includes exit pipes for both dual out rear and dual outside configurations so that you can choose the one that fits your style. Force II systems deliver a moderate exterior tone and moderate to mild interior tone, and are suited to customers looking for efficiency improvements without a lot of noise. Especially recommended for towing applications. Like all Flowmaster systems, the benefits include improved throttle response, power and mileage. Designed for an easy fit, this system includes all necessary parts and hardware for easy installation.\n\n\u2713 Mandrel bent 16 gauge 409 stainless tubing\n\u2713 Mild to moderate exterior exhaust tone\n\u2713 Includes hangers and hardware for easy installation\n\u2713 Connects after factory catalytic converter\n\u2713 Dyno tuned for maximum performance\n\u2713 Premium Flowmaster quality\n\n\nSubscribe to our Youtube channel:\nhttp:\/\/bit.ly\/1RuFMGB\n\nFor updates and new product releases, \u2018LIKE\u2019 us on Facebook: \nhttp:\/\/on.fb.me\/1K955xg\n\nFollow Flowmaster on Twitter:\nhttp:\/\/bit.ly\/1FBjnAu\n\nFollow Flowmaster on Instagram:\nhttp:\/\/bit.ly\/1LsFNvT",
    "referenceId": "bDcgsLbAaF8",
    "date_created": "1437427882",
    "date_modified": "1453397613",
    "tags": "Ford, F-150, Flowmaster, Exhaust, Muffler",
    "sourceId": "4",
    "VIDEO_LENGTH": "SHORT",
    "year": null,
    "make": "6",
    "model": "model-174",
    "brand_video": "50380",
    "category_video": null,
    "status": "approved",
    "department": "Exhaust, Mufflers & Tips",
    "featured_video": null,
    "visibility": "1",
    "VV_VI": "20",
    "CVV_VI": "4",
    "engagement_score": null,
    "conversion_score": null,
    "id": "10253442",
    "loginId": "1758237",
    "entityType": "1",
    "titleTextEncoded": "Flowmaster-Force-II-Cat-back-Exhaust-System-11-14-Ford-F-150-3-5L-EcoBoost-817539",
    "category": "",
    "duration": "43",
    "settings": "",
    "asset": {
        "type": "youtube",
        "thumbnailUrl": "https:\/\/i.ytimg.com\/vi\/bDcgsLbAaF8\/hqdefault.jpg",
        "uploadDate": 1437427882,
        "videoId": "bDcgsLbAaF8",
        "title": "Flowmaster Force II Cat-back Exhaust System 11-14 Ford F-150 3.5L EcoBoost - 817539",
        "description": "Questions? Give us a call (707) 544-4761\nView this product: http:\/\/bit.ly\/1fZppXj\nVisit Flowmaster's website: http:\/\/bit.ly\/1fyGZRh\n\nFlowmaster Part #817539\n\nTest Vehicle: 2014 Ford F-150 3.5L\n\nApplication:\n2011 to 2014 Ford F-150 with a 3.5L Eco Boost Turbo V6 engine, fits all wheelbases.\n\nFeatures:\nFor the person who wants the look of a traditional dual exhaust system with all the benefits that a Flowmaster Cat-back exhaust system provides, DOR\/S systems are the perfect choice. This system includes exit pipes for both dual out rear and dual outside configurations so that you can choose the one that fits your style. Force II systems deliver a moderate exterior tone and moderate to mild interior tone, and are suited to customers looking for efficiency improvements without a lot of noise. Especially recommended for towing applications. Like all Flowmaster systems, the benefits include improved throttle response, power and mileage. Designed for an easy fit, this system includes all necessary parts and hardware for easy installation.\n\n\u2713 Mandrel bent 16 gauge 409 stainless tubing\n\u2713 Mild to moderate exterior exhaust tone\n\u2713 Includes hangers and hardware for easy installation\n\u2713 Connects after factory catalytic converter\n\u2713 Dyno tuned for maximum performance\n\u2713 Premium Flowmaster quality\n\n\nSubscribe to our Youtube channel:\nhttp:\/\/bit.ly\/1RuFMGB\n\nFor updates and new product releases, \u2018LIKE\u2019 us on Facebook: \nhttp:\/\/on.fb.me\/1K955xg\n\nFollow Flowmaster on Twitter:\nhttp:\/\/bit.ly\/1FBjnAu\n\nFollow Flowmaster on Instagram:\nhttp:\/\/bit.ly\/1LsFNvT",
        "author": "Flowmaster Inc",
        "mediaDuration": "43",
        "prettyDuration": "00:00:43",
        "views": "3074"
    },
    "transcripts": "",
    "metrics_statistics": "{\"VV_VI\":{\"lastUpdatedDate\":\"2017-05-24\",\"engagement_score\":{\"lastUpdatedDate\":\"2017-05-25\"}},\"CVV_VI\":{\"lastUpdatedDate\":\"2017-05-24\",\"conversion_score\":{\"lastUpdatedDate\":\"2017-05-25\"}}}",
    "tvp_profiles": null,
    "tvp_profiles_manual": null,
    "tvp_profiles_maxscore": null
}