{
    "title": "Hennessey Venom GT 0-300km World Record Run - \/TUNED",
    "description": "Tuned joins the Hennessey team in Houston, TX as they attempt to set a new world record for the fastest accelerating production car from 0-300km\/hr.\n\nHennessey Venom GT: The World's Fastest Tuned Car - TUNED\nhttp:\/\/youtu.be\/8hDDBN_pIUQ",
    "referenceId": "74gthT8v1ds",
    "date_created": "1358798459",
    "date_modified": "1453835613",
    "tags": "",
    "sourceId": "4",
    "VIDEO_LENGTH": "LONG",
    "year": null,
    "make": null,
    "model": null,
    "brand_video": null,
    "category_video": null,
    "status": "approved",
    "department": null,
    "featured_video": null,
    "visibility": "1",
    "VV_VI": "12",
    "CVV_VI": null,
    "engagement_score": null,
    "conversion_score": null,
    "id": "25898318",
    "loginId": "1758237",
    "entityType": "1",
    "titleTextEncoded": "Hennessey-Venom-GT-0-300km-World-Record-Run-TUNED",
    "category": "",
    "duration": "487",
    "settings": "",
    "asset": {
        "type": "youtube",
        "thumbnailUrl": "https:\/\/i.ytimg.com\/vi\/74gthT8v1ds\/hqdefault.jpg",
        "uploadDate": 1358798459,
        "videoId": "74gthT8v1ds",
        "title": "Hennessey Venom GT 0-300km World Record Run - \/TUNED",
        "description": "Tuned joins the Hennessey team in Houston, TX as they attempt to set a new world record for the fastest accelerating production car from 0-300km\/hr.\n\nHennessey Venom GT: The World's Fastest Tuned Car - TUNED\nhttp:\/\/youtu.be\/8hDDBN_pIUQ",
        "author": "\/DRIVE",
        "mediaDuration": "487",
        "prettyDuration": "00:08:07",
        "views": "2073451"
    },
    "transcripts": "",
    "metrics_statistics": "{\"VV_VI\":{\"lastUpdatedDate\":\"2017-05-24\",\"engagement_score\":{\"lastUpdatedDate\":\"2017-05-25\"}}}",
    "tvp_profiles": null,
    "tvp_profiles_manual": null,
    "tvp_profiles_maxscore": null
}