{
    "title": "Trailer Hitch Install: CURT 16022 RAM OEM 5th Wheel Roller Adapter",
    "description": "This video depicts the assembly and installation of the CURT 16022 Ram OEM 5th Wheel Roller Adapter, in combination with the 16570 R24 5th Wheel Roller and the 16545 Q24 5th Wheel Hitch Head.  The 16022 is compatible with the following roller models: 16550, 16560, 16570.\n\nInstall Sheet - https:\/\/www.curtmfg.com\/masterlibrary\/16022\/installsheet\/CM_16022_INS.PDF\n\nFeatures:\n\n- Adapts any CURT 5th Wheel Roller to fit RAM OEM under-bed hitch platform.\n\n- Quarter-Turn Anchoring System provides quick installation and removal.\n\n- Adjustable anchors to eliminate chucking between the legs and under-bed rails.\n\n- Meets or exceeds current and proposed industry standards.\n\n- Protected by a highly durable carbide powder coat finish.\n\n- Backed by a 10-year limited warranty.\n\n\nRead and understand instructions before using this product. Fully instruct and demonstrate the operation of this 5th wheel hitch to the end user. Include the importance of observing all warnings contained herein, including warning labels on 5th wheel hitch mid section. Provide this manual in its entirety to the end-user. Serious injury or death may result if the warnings above are not observed.\n\nWarning:\n-This video is intended to be used as reference. Please refer to print instructions for complete installation information.",
    "referenceId": "DyiuXg4kKT8",
    "date_created": "1440531520",
    "date_modified": "1457395385",
    "tags": "CURT Trailer hitch, 5th wheel roller adapter, how to install, Dodge Ram",
    "sourceId": "4",
    "VIDEO_LENGTH": "SHORT",
    "year": null,
    "make": "23",
    "model": "model-224",
    "brand_video": "56189",
    "category_video": null,
    "status": "approved",
    "department": "Trailer Hitches",
    "featured_video": null,
    "visibility": "1",
    "VV_VI": "3",
    "CVV_VI": null,
    "engagement_score": null,
    "conversion_score": null,
    "id": "26090871",
    "loginId": "1758237",
    "entityType": "1",
    "titleTextEncoded": "Trailer-Hitch-Install-CURT-16022-RAM-OEM-5th-Wheel-Roller-Adapter",
    "category": "",
    "duration": 155,
    "settings": "",
    "asset": {
        "type": "youtube",
        "thumbnailUrl": "https:\/\/i.ytimg.com\/vi\/DyiuXg4kKT8\/hqdefault.jpg",
        "uploadDate": 1440531520,
        "videoId": "DyiuXg4kKT8",
        "title": "Trailer Hitch Install: CURT 16022 RAM OEM 5th Wheel Roller Adapter",
        "description": "http:\/\/www.curtmfg.com\n\nThis video depicts the assembly and installation of the CURT 16022 Ram OEM  5th Wheel Roller Adapter, in combination with the 16570 R24 5th Wheel Roller and the 16545 Q24 5th Wheel Hitch Head.  The 16022 is compatible with the following roller models: 16550, 16560, 16570.\n\nInstall Sheet - https:\/\/www.curtmfg.com\/masterlibrary\/16022\/installsheet\/CM_16022_INS.PDF\n\nFeatures:\n\n- Adapts any CURT 5th Wheel Roller to fit RAM OEM under-bed hitch platform.\n\n- Quarter-Turn Anchoring System provides quick installation and removal.\n\n- Adjustable anchors to eliminate chucking between the legs and under-bed rails.\n\n- Meets or exceeds current and proposed industry standards.\n\n- Protected by a highly durable carbide powder coat finish.\n\n- Backed by a 10-year limited warranty.\n\n\nRead and understand instructions before using this product. Fully instruct and demonstrate the operation of this 5th wheel hitch to the end user. Include the importance of observing all warnings contained herein, including warning labels on 5th wheel hitch mid section. Provide this manual in its entirety to the end-user. Serious injury or death may result if the warnings above are not observed.\n\nWarning:\n-This video is intended to be used as reference. Please refer to print instructions for complete installation information.\n-Need help or have some questions? Call Technical Support at 800.798.0813 (Monday-Friday 8am-7pm CST)",
        "author": "CURT Manufacturing",
        "mediaDuration": 155,
        "prettyDuration": "00:02:35",
        "views": "504",
        "uploadAsset": false,
        "quality": ""
    },
    "transcripts": "",
    "metrics_statistics": "{\"VV_VI\":{\"lastUpdatedDate\":\"2017-05-24\",\"engagement_score\":{\"lastUpdatedDate\":\"2017-05-25\"}}}",
    "tvp_profiles": null,
    "tvp_profiles_manual": null,
    "tvp_profiles_maxscore": null
}