{
    "title": "Trailer Hitch Install: CURT 13535 on a Honda CR-V",
    "description": "This video depicts the installation of the CURT 13535 class 3 trailer hitch on a 2004 Honda CR-V. \n\nInstall Sheet - \nhttps:\/\/www.curtmfg.com\/masterlibrary\/13535\/installsheet\/CM_13535_INS.PDF\n\nApplication Coverage:\n2002-2006 Honda CR-V\n\nSpecial Notes:\n***DO NOT EXCEED VEHICLE MANUFACTURER'S RECOMMENDED TOWING CAPACITY***\nPERIODICALLY CHECK THIS RECEIVER HITCH TO ENSURE THAT ALL FASTENERS\nARE TIGHT AND THAT ALL STRUCTURAL COMPONENTS ARE SOUND.\n\nWarning:\n-This video is intended to be used as reference. Please refer to print instructions for complete installation information.",
    "referenceId": "EETYLB3p3MQ",
    "date_created": "1429220361",
    "date_modified": "1458768991",
    "tags": "CURT Receiver Hitch, trailer hitches, towing, how to install, Honda CR-V, curt 13535",
    "sourceId": "4",
    "VIDEO_LENGTH": "SHORT",
    "year": null,
    "make": "10",
    "model": "model-161",
    "brand_video": "56189",
    "category_video": null,
    "status": "approved",
    "department": "Trailer Hitches",
    "featured_video": null,
    "visibility": "1",
    "VV_VI": "1",
    "CVV_VI": null,
    "engagement_score": null,
    "conversion_score": null,
    "id": "26090895",
    "loginId": "1758237",
    "entityType": "1",
    "titleTextEncoded": "Trailer-Hitch-Install-CURT-13535-on-a-Honda-CR-V",
    "category": "",
    "duration": 208,
    "settings": "",
    "asset": {
        "type": "youtube",
        "thumbnailUrl": "https:\/\/i.ytimg.com\/vi\/EETYLB3p3MQ\/hqdefault.jpg",
        "uploadDate": 1429220361,
        "videoId": "EETYLB3p3MQ",
        "title": "Trailer Hitch Install: CURT 13535 on a Honda CR-V",
        "description": "http:\/\/www.curtmfg.com\nThis video depicts the installation of the CURT 13535 class 3 trailer hitch on a 2004 Honda CR-V. \n\nInstall Sheet - \nhttps:\/\/www.curtmfg.com\/masterlibrary\/13535\/installsheet\/CM_13535_INS.PDF\n\nApplication Coverage:\n2002-2006 Honda CR-V\n\nSpecial Notes:\n***DO NOT EXCEED VEHICLE MANUFACTURER'S RECOMMENDED TOWING CAPACITY***\nPERIODICALLY CHECK THIS RECEIVER HITCH TO ENSURE THAT ALL FASTENERS\nARE TIGHT AND THAT ALL STRUCTURAL COMPONENTS ARE SOUND.\n\nWarning:\n-This video is intended to be used as reference. Please refer to print instructions for complete installation information.\n-Need help or have some questions? Call Technical Support at 800.798.0813 (Monday-Friday 8am-7pm CST)",
        "author": "CURT Manufacturing",
        "mediaDuration": 208,
        "prettyDuration": "00:03:28",
        "views": "1029",
        "uploadAsset": false,
        "quality": ""
    },
    "transcripts": "",
    "metrics_statistics": "{\"VV_VI\":{\"lastUpdatedDate\":\"2017-05-24\",\"engagement_score\":{\"lastUpdatedDate\":\"2017-05-25\"}}}",
    "tvp_profiles": null,
    "tvp_profiles_manual": null,
    "tvp_profiles_maxscore": null
}