{
    "title": "Trailer Hitch Install: CURT 15303 on 1997 Ford F-150",
    "description": "This video depicts the installation of the CURT 15303 class V trailer hitch on a 1997 Ford F-150.\n\nInstall Sheet - https:\/\/www.curtmfg.com\/masterlibrary\/15303\/installsheet\/CM_15303_INS.PDF\n\nApplication Coverage:\n1997 - 2003 Ford F-150\n\nSpecial Notes:\n***DO NOT EXCEED VEHICLE MANUFACTURER'S RECOMMENDED TOWING CAPACITY***\nPERIODICALLY CHECK THIS RECEIVER HITCH TO ENSURE THAT ALL FASTENERS\nARE TIGHT AND THAT ALL STRUCTURAL COMPONENTS ARE SOUND.\n*** USE EXISTING VEHICLE HARDWARE ***\n\nWarning:\n-This video is intended to be used as reference. Please refer to print instructions for complete installation information.",
    "referenceId": "rhxV5raTFOQ",
    "date_created": "1389658000",
    "date_modified": "1458847789",
    "tags": "CURT Receiver Hitch, trailer hitch, towing, how to install, curt 15303, Ford F-150, F150",
    "sourceId": "4",
    "VIDEO_LENGTH": "SHORT",
    "year": null,
    "make": "6",
    "model": "model-174",
    "brand_video": "56189",
    "category_video": null,
    "status": "approved",
    "department": "Trailer Hitches",
    "featured_video": null,
    "visibility": "1",
    "VV_VI": "40",
    "CVV_VI": null,
    "engagement_score": null,
    "conversion_score": null,
    "id": "26091009",
    "loginId": "1758237",
    "entityType": "1",
    "titleTextEncoded": "Trailer-Hitch-Install-CURT-15303-on-1997-Ford-F-150",
    "category": "",
    "duration": 116,
    "settings": "",
    "asset": {
        "type": "youtube",
        "thumbnailUrl": "https:\/\/i.ytimg.com\/vi\/rhxV5raTFOQ\/hqdefault.jpg",
        "uploadDate": 1389658000,
        "videoId": "rhxV5raTFOQ",
        "title": "Trailer Hitch Install: CURT 15303 on 1997 Ford F-150",
        "description": "http:\/\/www.curtmfg.com\n\nThis video depicts the installation of the CURT 15303 class V trailer hitch on a 1997 Ford F-150.\n\nInstall Sheet - https:\/\/www.curtmfg.com\/masterlibrary\/15303\/installsheet\/CM_15303_INS.PDF\n\nApplication Coverage:\n1997 - 2003 Ford F-150\n\nSpecial Notes:\n***DO NOT EXCEED VEHICLE MANUFACTURER'S RECOMMENDED TOWING CAPACITY***\nPERIODICALLY CHECK THIS RECEIVER HITCH TO ENSURE THAT ALL FASTENERS\nARE TIGHT AND THAT ALL STRUCTURAL COMPONENTS ARE SOUND.\n*** USE EXISTING VEHICLE HARDWARE ***\n\nWarning:\n-This video is intended to be used as reference. Please refer to print instructions for complete installation information.\n-Need help or have some questions? Call Technical Support at 800.798.0813 (Monday-Friday 8am-7pm CST)",
        "author": "CURT Manufacturing",
        "mediaDuration": 116,
        "prettyDuration": "00:01:56",
        "views": "1240",
        "uploadAsset": false,
        "quality": ""
    },
    "transcripts": "",
    "metrics_statistics": "{\"VV_VI\":{\"lastUpdatedDate\":\"2017-05-24\",\"engagement_score\":{\"lastUpdatedDate\":\"2017-05-25\"}}}",
    "tvp_profiles": null,
    "tvp_profiles_manual": null,
    "tvp_profiles_maxscore": null
}