{
    "title": "EBC Procut",
    "description": "How to turn slotted rotors using a Procut on car lathe and cure Disc Run Out and brake vibration.",
    "referenceId": "GmhaTzfJ_Ps",
    "date_created": "1253005541",
    "date_modified": "1459185258",
    "tags": "EBC Brakes, slotted rotors, how to turn slotted rotors, Procut brake lathe",
    "sourceId": "4",
    "VIDEO_LENGTH": "LONG",
    "year": null,
    "make": null,
    "model": null,
    "brand_video": "50677",
    "category_video": null,
    "status": "approved",
    "department": "Brakes, Rotors & Pads",
    "featured_video": null,
    "visibility": "1",
    "VV_VI": "34",
    "CVV_VI": "2",
    "engagement_score": null,
    "conversion_score": null,
    "id": "59880338",
    "loginId": "1758237",
    "entityType": "1",
    "titleTextEncoded": "EBC-Procut",
    "category": "",
    "duration": 377,
    "settings": "",
    "asset": {
        "type": "youtube",
        "thumbnailUrl": "https:\/\/i.ytimg.com\/vi\/GmhaTzfJ_Ps\/hqdefault.jpg",
        "uploadDate": 1253005541,
        "videoId": "GmhaTzfJ_Ps",
        "title": "EBC Procut",
        "description": "How to turn slotted rotors using a Procut on car lathe and cure Disc Run Out and brake vibration.",
        "author": "EBCBrakesUK",
        "mediaDuration": 377,
        "prettyDuration": "00:06:17",
        "views": "15834",
        "uploadAsset": false,
        "quality": ""
    },
    "transcripts": "",
    "metrics_statistics": "{\"VV_VI\":{\"lastUpdatedDate\":\"2017-05-24\",\"engagement_score\":{\"lastUpdatedDate\":\"2017-05-25\"}},\"CVV_VI\":{\"lastUpdatedDate\":\"2017-05-24\",\"conversion_score\":{\"lastUpdatedDate\":\"2017-05-25\"}}}",
    "tvp_profiles": null,
    "tvp_profiles_manual": null,
    "tvp_profiles_maxscore": null
}