{
    "title": "Porsche 911 991.2 Up Volcano Mountain -- \/DRIVEN",
    "description": "Has the new, turbocharged Porsche 911 Carrera changed everything, or just some of the things? The\/DRIVE's Mike Spinelli heads to Mount Teide on the volcanic island of Tenerife to find out.",
    "referenceId": "GpJofAean6U",
    "date_created": "1461942002",
    "date_modified": "1470694505",
    "tags": "Porsche 911, 991.2, porsche, first drive, Porsche test drive",
    "sourceId": "4",
    "VIDEO_LENGTH": "LONG",
    "year": null,
    "make": "4",
    "model": null,
    "brand_video": null,
    "category_video": null,
    "status": "approved",
    "department": null,
    "featured_video": null,
    "visibility": "1",
    "VV_VI": null,
    "CVV_VI": null,
    "engagement_score": null,
    "conversion_score": null,
    "id": "65631899",
    "loginId": "1758237",
    "entityType": "1",
    "titleTextEncoded": "Porsche-911-991-2-Up-Volcano-Mountain-DRIVEN",
    "category": "",
    "duration": 534,
    "settings": "",
    "asset": {
        "type": "youtube",
        "thumbnailUrl": "https:\/\/i.ytimg.com\/vi\/GpJofAean6U\/hqdefault.jpg",
        "uploadDate": 1461942002,
        "videoId": "GpJofAean6U",
        "title": "Porsche 911 991.2 Up Volcano Mountain -- \/DRIVEN",
        "description": "Has the new, turbocharged Porsche 911 Carrera changed everything, or just some of the things? The\/DRIVE's Mike Spinelli heads to Mount Teide on the volcanic island of Tenerife to find out.\n\nMore at The\/DRIVE:\nhttp:\/\/www.thedrive.com",
        "author": "\/DRIVE",
        "mediaDuration": 534,
        "prettyDuration": "00:08:54",
        "views": "34488",
        "uploadAsset": false,
        "quality": ""
    },
    "transcripts": "",
    "metrics_statistics": null,
    "tvp_profiles": null,
    "tvp_profiles_manual": null,
    "tvp_profiles_maxscore": null
}