{
    "title": "2012 Ford F-150 V6 3.5L Eco Boost Turbo - MagnaFlow Exhaust Part #15458",
    "description": "2012 Ford F-150 V6 3.5L Eco Boost Turbo - MagnaFlow Exhaust Part #15458",
    "referenceId": "X_8hFccdTGc",
    "date_created": "1303492653",
    "date_modified": "1453742038",
    "tags": "Magnaflow, 2012 Ford F-150, EcoBoost, performance exhaust, Ford F-150 Exhaust Sound",
    "sourceId": "4",
    "VIDEO_LENGTH": "SHORT",
    "year": null,
    "make": "6",
    "model": "model-174",
    "brand_video": "50221",
    "category_video": null,
    "status": "approved",
    "department": "Exhaust, Mufflers & Tips",
    "featured_video": null,
    "visibility": "1",
    "VV_VI": "18",
    "CVV_VI": null,
    "engagement_score": null,
    "conversion_score": null,
    "id": "6650118",
    "loginId": "1758237",
    "entityType": "1",
    "titleTextEncoded": "2012-Ford-F-150-V6-3-5L-Eco-Boost-Turbo-MagnaFlow-Exhaust-Part-15458",
    "category": null,
    "duration": "21",
    "settings": null,
    "asset": {
        "type": "youtube",
        "thumbnailUrl": "https:\/\/i.ytimg.com\/vi\/X_8hFccdTGc\/hqdefault.jpg",
        "uploadDate": 1303492653,
        "videoId": "X_8hFccdTGc",
        "title": "2012 Ford F-150 V6 3.5L Eco Boost Turbo - MagnaFlow Exhaust Part #15458",
        "description": "2012 Ford F-150 V6 3.5L Eco Boost Turbo - MagnaFlow Exhaust Part #15458\n\nLearn more: http:\/\/www.magnaflow.com\/02product\/displayapplications.asp?partnumber=15458\n\nSubscribe to our channel!\nhttp:\/\/www.youtube.com\/subscription_center?add_user=magnaflowtv\n\nVisit our website and learn more about products: \nhttp:\/\/MagnaFlow.com\n\nDon't miss out on any upcoming events or arrivals: \nhttp:\/\/facebook.com\/MagnaFlow\n\nFollow MagnaFlow on Twitter:\nhttp:\/\/twitter.com\/MagnaFlow",
        "author": "magnaflowtv",
        "mediaDuration": "21",
        "prettyDuration": "00:00:21",
        "views": "2875"
    },
    "transcripts": null,
    "metrics_statistics": "{\"VV_VI\":{\"lastUpdatedDate\":\"2017-05-24\",\"engagement_score\":{\"lastUpdatedDate\":\"2017-05-25\"}}}",
    "tvp_profiles": null,
    "tvp_profiles_manual": null,
    "tvp_profiles_maxscore": null
}