{
    "title": "How To Install a K&N Air Intake on a 2015 Dodge Ram 1500 3.0L Diesel",
    "description": "See how easy it is to install a K&N air intake on your 2015 Dodge Ram 1500 3.0L Diesel.\n\nK&N 63-1571 performance air intake system is easy to install and guaranteed to increase horsepower in 2015 Dodge Ram 1500 with a 3.0L diesel engine. When dyno tested, this air intake created an estimated gain of 11.22 horsepower at 3300 RPM.\n\nThis air intake includes an oversized washable & reusable air filter that can go up to 100,000 miles between servicing. K&N air intake 63-1571 also includes a rotomolded polyethylene air intake tube and aluminum heat shield designed to increase air flow and isolate intake air from engine heat.",
    "referenceId": "w3JKgXk77KA",
    "date_created": "1471907912",
    "date_modified": "1472583448",
    "tags": "K&N Cold Air Intake, Dodge Ram 1500, Dodge Ram Diesel, how to install k&n intake, CAI, RAM",
    "sourceId": "4",
    "VIDEO_LENGTH": "LONG",
    "year": null,
    "make": "23",
    "model": "model-224",
    "brand_video": "56817",
    "category_video": null,
    "status": "approved",
    "department": "Air Intake Systems",
    "featured_video": null,
    "visibility": "1",
    "VV_VI": "2",
    "CVV_VI": null,
    "engagement_score": null,
    "conversion_score": null,
    "id": "67595775",
    "loginId": "1758237",
    "entityType": "1",
    "titleTextEncoded": "How-To-Install-a-K-N-Air-Intake-on-a-2015-Dodge-Ram-1500-3-0L-Diesel",
    "category": "",
    "duration": 269,
    "settings": {},
    "asset": {
        "type": "youtube",
        "thumbnailUrl": "https:\/\/i.ytimg.com\/vi\/w3JKgXk77KA\/hqdefault.jpg",
        "uploadDate": 1471907912,
        "videoId": "w3JKgXk77KA",
        "title": "How To Install a K&N Air Intake on a 2015 Dodge Ram 1500 3.0L Diesel",
        "description": "See how easy it is to install a K&N air intake on your 2015 Dodge Ram 1500 3.0L Diesel.\n\nK&N 63-1571 performance air intake system is easy to install and guaranteed to increase horsepower in 2015 Dodge Ram 1500 with a 3.0L diesel engine. When dyno tested, this air intake created an estimated gain of 11.22 horsepower at 3300 RPM.\n\nThis air intake includes an oversized washable & reusable air filter that can go up to 100,000 miles between servicing. K&N air intake 63-1571 also includes a rotomolded polyethylene air intake tube and aluminum heat shield designed to increase air flow and isolate intake air from engine heat.\n\nMore information on this air intake system:\nhttp:\/\/www.knfilters.com\/search\/product.aspx?prod=63-1571\n\nSearch for an air intake for a different vehicle:\nhttp:\/\/www.knfilters.com\/search\/appsearch.aspx",
        "author": "KNfilters",
        "mediaDuration": 269,
        "prettyDuration": "00:04:29",
        "views": "18",
        "uploadAsset": false,
        "quality": ""
    },
    "transcripts": "",
    "metrics_statistics": "{\"VV_VI\":{\"lastUpdatedDate\":\"2017-05-24\",\"engagement_score\":{\"lastUpdatedDate\":\"2017-05-25\"}}}",
    "tvp_profiles": null,
    "tvp_profiles_manual": null,
    "tvp_profiles_maxscore": null
}