{
    "title": "2012, 2013 & 2014 Chevy Camaro ZL1 6.2L Air Intake Installation",
    "description": "See how easy it is to add more performance to the 2012 and 2013 Chevy Camaro ZL1 6.2L.\n\nK&N 63-3079 air intake modification showed an estimated gain of 31.7 horsepower at 4300 RPM when tested on the K&N dynamometer.\n\nK&N 63-3079 fits the following: \n2014 CHEVROLET CAMARO ZL1 6.2L V8 \n2013 CHEVROLET CAMARO ZL1 6.2L V8\n2012 CHEVROLET CAMARO ZL1 6.2L V8",
    "referenceId": "eWrMGw9SSVs",
    "date_created": "1384967598",
    "date_modified": "1455309308",
    "tags": "K&N Air Intake System, Chevy Camaro ZL1, 2012,2013,2014, how to install, cold air intake",
    "sourceId": "4",
    "VIDEO_LENGTH": "LONG",
    "year": null,
    "make": "115",
    "model": "model-2680",
    "brand_video": "56817",
    "category_video": null,
    "status": "approved",
    "department": "Air Intake Systems",
    "featured_video": null,
    "visibility": "1",
    "VV_VI": "6",
    "CVV_VI": null,
    "engagement_score": null,
    "conversion_score": null,
    "id": "6806718",
    "loginId": "1758237",
    "entityType": "1",
    "titleTextEncoded": "2012-2013-2014-Chevy-Camaro-ZL1-6-2L-Air-Intake-Installation",
    "category": "",
    "duration": "325",
    "settings": "",
    "asset": {
        "type": "youtube",
        "thumbnailUrl": "https:\/\/i.ytimg.com\/vi\/eWrMGw9SSVs\/hqdefault.jpg",
        "uploadDate": 1384967598,
        "videoId": "eWrMGw9SSVs",
        "title": "2012, 2013 & 2014 Chevy Camaro ZL1 6.2L Air Intake Installation",
        "description": "See how easy it is to add more performance to the 2012 and 2013 Chevy Camaro ZL1 6.2L.\n\nhttp:\/\/www.knfilters.com\/search\/product.aspx?prod=63-3079\n\nK&N 63-3079 air intake modification showed an estimated gain of 31.7 horsepower at 4300 RPM when tested on the K&N dynamometer.\n\nK&N 63-3079 fits the following: \n2014 CHEVROLET CAMARO ZL1 6.2L V8 \n2013 CHEVROLET CAMARO ZL1 6.2L V8\n2012 CHEVROLET CAMARO ZL1 6.2L V8 \n\nCheck http:\/\/www.knfilters.com\/search\/product.aspx?prod=63-3079 for more information and an up to date list of models this air intake fits\n\nSearch for your own vehicle's corresponding cold air intake or air filter here:\nhttp:\/\/www.KNfilters.com",
        "author": "KNfilters",
        "mediaDuration": "325",
        "prettyDuration": "00:05:25",
        "views": "5397"
    },
    "transcripts": "",
    "metrics_statistics": "{\"VV_VI\":{\"lastUpdatedDate\":\"2017-05-24\",\"engagement_score\":{\"lastUpdatedDate\":\"2017-05-25\"}}}",
    "tvp_profiles": null,
    "tvp_profiles_manual": null,
    "tvp_profiles_maxscore": null
}