{
    "title": "US Lawn Mower Racing Finals",
    "description": "Lawn mower racing is one of the last affordable action sports. Lawn mower racers know the value of good filtration, that is why K&N is nearly everywhere on the track. K&N caught up with these weekend warriors at the 17th Annual STA-BIL Nationals in Delaware, Ohio at the Delaware County Fairgrounds.",
    "referenceId": "TlWxD7iUIXk",
    "date_created": "1253540944",
    "date_modified": "1463695889",
    "tags": "",
    "sourceId": "4",
    "VIDEO_LENGTH": "SHORT",
    "year": null,
    "make": null,
    "model": null,
    "brand_video": null,
    "category_video": null,
    "status": "approved",
    "department": null,
    "featured_video": null,
    "visibility": "1",
    "VV_VI": null,
    "CVV_VI": null,
    "engagement_score": null,
    "conversion_score": null,
    "id": "6807010",
    "loginId": "1758237",
    "entityType": "1",
    "titleTextEncoded": "US-Lawn-Mower-Racing-Finals",
    "category": "",
    "duration": "145",
    "settings": "",
    "asset": {
        "type": "youtube",
        "thumbnailUrl": "https:\/\/i.ytimg.com\/vi\/TlWxD7iUIXk\/hqdefault.jpg",
        "uploadDate": 1253540944,
        "videoId": "TlWxD7iUIXk",
        "title": "US Lawn Mower Racing Finals",
        "description": "Lawn mower racing is one of the last affordable action sports. Lawn mower racers know the value of good filtration, that is why K&N is nearly everywhere on the track. K&N caught up with these weekend warriors at the 17th Annual STA-BIL Nationals in Delaware, Ohio at the Delaware County Fairgrounds.\n\nhttp:\/\/www.KNfilters.com",
        "author": "KNfilters",
        "mediaDuration": "145",
        "prettyDuration": "00:02:25",
        "views": "53245",
        "uploadAsset": false,
        "quality": ""
    },
    "transcripts": "",
    "metrics_statistics": null,
    "tvp_profiles": null,
    "tvp_profiles_manual": null,
    "tvp_profiles_maxscore": null
}