{
    "title": "Canvasback Inc. - U.S. Made Cargo Liners",
    "description": "",
    "referenceId": "y5odsMCHYGE",
    "date_created": "1484763937",
    "date_modified": "1484763937",
    "tags": null,
    "sourceId": "4",
    "VIDEO_LENGTH": "SHORT",
    "year": null,
    "make": null,
    "model": null,
    "brand_video": null,
    "category_video": null,
    "status": "approved",
    "department": null,
    "featured_video": null,
    "visibility": "1",
    "VV_VI": null,
    "CVV_VI": null,
    "engagement_score": null,
    "conversion_score": null,
    "id": "85040470",
    "loginId": "1758237",
    "entityType": "1",
    "titleTextEncoded": "Canvasback-Inc-U-S-Made-Cargo-Liners",
    "category": null,
    "duration": 138,
    "settings": null,
    "asset": {
        "type": "youtube",
        "author": "Samantha Hanus",
        "hdvFlag": 1,
        "description": "",
        "tags": "",
        "thumbnailUrl": "https:\/\/i.ytimg.com\/vi\/y5odsMCHYGE\/hqdefault.jpg",
        "videoId": "y5odsMCHYGE",
        "mediaDuration": 138,
        "prettyDuration": "00:02:18"
    },
    "transcripts": null,
    "metrics_statistics": null,
    "tvp_profiles": null,
    "tvp_profiles_manual": null,
    "tvp_profiles_maxscore": null
}